musicjson/__init__.py
musicjson/band.py
musicjson-0.0.2.dist-info/LICENSE
musicjson-0.0.2.dist-info/METADATA
musicjson-0.0.2.dist-info/WHEEL
musicjson-0.0.2.dist-info/top_level.txt
musicjson-0.0.2.dist-info/RECORD
