Metadata-Version: 2.1
Name: musicjson
Version: 0.0.2
Summary: Play with sound: compose notes in JSON and play it
Home-page: https://github.com/DavidWang2AI/musicjson
Author: David Wang
Author-email: davidwang.2ai@gmail.com
License: MIT
Project-URL: Bug Tracker, https://github.com/DavidWang2AI/musicjson/issues
Platform: UNKNOWN
Classifier: Programming Language :: Python :: 3
Classifier: License :: OSI Approved :: MIT License
Classifier: Operating System :: OS Independent
Requires-Python: >=3.6
License-File: LICENSE
Requires-Dist: numpy
Requires-Dist: sounddevice
Requires-Dist: SoundFile
